[
  {
    "id": 1,
    "nombre": "Nalga",
    "categoria": "vacuno",
    "img": "img/producto-01.jpg",
    "precio": 900
  },
  {
    "id": 2,
    "nombre": "Bola de lomo",
    "categoria": "vacuno",
    "img": "img/producto-02.jpg",
    "precio": 780
  },
  {
    "id": 3,
    "nombre": "Colita de Cuadril",
    "categoria": "vacuno",
    "img": "img/producto-03.jpg",
    "precio": 650
  },
  {
    "id": 4,
    "nombre": "Lomo",
    "categoria": "vacuno",
    "img": "img/producto-04.jpg",
    "precio": 550
  },
  {
    "id": 5,
    "nombre": "Pata muslo",
    "categoria": "aves",
    "img": "img/producto-05.jpg",
    "precio": 720
  },
  {
    "id": 6,
    "nombre": "Pechuga",
    "categoria": "aves",
    "img": "img/producto-06.jpg",
    "precio": 720
  },
  {
    "id": 7,
    "nombre": "Pollo",
    "categoria": "aves",
    "img": "img/producto-07.jpg",
    "precio": 630
  },
  {
    "id": 8,
    "nombre": "Bondiola",
    "categoria": "cerdo",
    "img": "img/producto-08.jpg",
    "precio": 550
  },
  {
    "id": 9,
    "nombre": "Costeleta",
    "categoria": "cerdo",
    "img": "img/producto-09.jpg",
    "precio": 550
  },
  {
    "id": 10,
    "nombre": "Pechito",
    "categoria": "cerdo",
    "img": "img/producto-10.jpg",
    "precio": 630
  },
  {
    "id": 11,
    "nombre": "Chorizo de cerdo",
    "categoria": "embutidos",
    "img": "img/producto-11.jpg",
    "precio": 550
  },
  {
    "id": 12,
    "nombre": "Salchicha parrillera",
    "categoria": "embutidos",
    "img": "img/producto-12.jpg",
    "precio": 720
  },
  {
    "id": 13,
    "nombre": "Molleja",
    "categoria": "achuras",
    "img": "img/producto-13.jpg",
    "precio": 630
  },
  {
    "id": 14,
    "nombre": "Chinchulin",
    "categoria": "achuras",
    "img": "img/producto-14.jpg",
    "precio": 720
  },
  {
    "id": 15,
    "nombre": "Carne Molida",
    "categoria": "ofertas",
    "img": "img/producto-15.jpg",
    "precio": 630
  }
]
